pypocketmap/abstract.h
pypocketmap/packed.h
pypocketmap/flags.h
pypocketmap/optimization.h
pypocketmap/__init__.py
pypocketmap/polymur-hash.h
pypocketmap/simd.h
pypocketmap/bits.h
pypocketmap/__init__.pyi
pypocketmap/py.typed
pypocketmap/_pkt_c/str_int32.pyi
pypocketmap/_pkt_c/str_int64.pyi
pypocketmap/_pkt_c/str_float64.pyi
pypocketmap/_pkt_c/__init__.py
pypocketmap/_pkt_c/str_str.pyi
pypocketmap/_pkt_c/str_float32.pyi
pypocketmap/_pkt_c/int64_int64.pyi
pypocketmap-0.0.1rc1.dist-info/top_level.txt
pypocketmap-0.0.1rc1.dist-info/RECORD
pypocketmap-0.0.1rc1.dist-info/LICENSE
pypocketmap-0.0.1rc1.dist-info/METADATA
pypocketmap-0.0.1rc1.dist-info/WHEEL
_pkt_c/str_int32.cpython-311-x86_64-linux-gnu.so
_pkt_c/str_float64.cpython-311-x86_64-linux-gnu.so
_pkt_c/str_float32.cpython-311-x86_64-linux-gnu.so
_pkt_c/str_str.cpython-311-x86_64-linux-gnu.so
_pkt_c/str_int64.cpython-311-x86_64-linux-gnu.so
_pkt_c/int64_int64.cpython-311-x86_64-linux-gnu.so
